bert_document_classification/__init__.py
bert_document_classification/document_bert.py
bert_document_classification/document_bert_architectures.py
bert_document_classification/transformer.py
bert_document_classification/models/__init__.py
bert_document_classification/models/obesity_document_bert.py
bert_document_classification/models/smoker_document_bert.py
bert_document_classification/models/util.py
bert_document_classification-1.0.0.dist-info/METADATA
bert_document_classification-1.0.0.dist-info/WHEEL
bert_document_classification-1.0.0.dist-info/top_level.txt
bert_document_classification-1.0.0.dist-info/RECORD
