Metadata-Version: 2.1
Name: bert-document-classification
Version: 1.0.0
Summary: long document classification with language models
Home-page: https://github.com/AndriyMulyar/bert_document_classification
Author: Andriy Mulyar, Elliot Schumacher, Masoud Rouhizadeh and Mark Dredze
Author-email: contact@andriymulyar.com
License: MIT
Keywords: BERT,document classification
Platform: UNKNOWN
Classifier: Development Status :: 4 - Beta
Classifier: License :: OSI Approved :: MIT License
Classifier: Programming Language :: Python :: 3.5
Classifier: Natural Language :: English
Classifier: Topic :: Text Processing :: Linguistic
Classifier: Intended Audience :: Science/Research
Requires-Dist: pytorch-transformers
Requires-Dist: torch
Requires-Dist: configargparse
Requires-Dist: scikit-learn
